redtrio/__init__.py
redtrio/lowlevel/__init__.py
redtrio/lowlevel/client.py
redtrio/lowlevel/connections.py
redtrio/midlevel/__init__.py
redtrio/midlevel/client.py
redtrio-0.6.3.dist-info/WHEEL
redtrio-0.6.3.dist-info/METADATA
redtrio-0.6.3.dist-info/RECORD
